CHANGES.rst
MANIFEST.in
README.rst
setup.cfg
setup.py
Products/__init__.py
Products.DataGridField.egg-info/PKG-INFO
Products.DataGridField.egg-info/SOURCES.txt
Products.DataGridField.egg-info/dependency_links.txt
Products.DataGridField.egg-info/namespace_packages.txt
Products.DataGridField.egg-info/not-zip-safe
Products.DataGridField.egg-info/requires.txt
Products.DataGridField.egg-info/top_level.txt
Products/DataGridField/CheckboxColumn.py
Products/DataGridField/ColorColumn.py
Products/DataGridField/Column.py
Products/DataGridField/DataGridField.py
Products/DataGridField/DataGridWidget.py
Products/DataGridField/DateColumn.py
Products/DataGridField/DatetimeColumn.py
Products/DataGridField/DatetimeLocalColumn.py
Products/DataGridField/EmailColumn.py
Products/DataGridField/FileColumn.py
Products/DataGridField/FixedColumn.py
Products/DataGridField/HelpColumn.py
Products/DataGridField/LinesColumn.py
Products/DataGridField/LinkColumn.py
Products/DataGridField/MonthColumn.py
Products/DataGridField/PasswordColumn.py
Products/DataGridField/RadioColumn.py
Products/DataGridField/RangeColumn.py
Products/DataGridField/SearchColumn.py
Products/DataGridField/SelectColumn.py
Products/DataGridField/TimeColumn.py
Products/DataGridField/UrlColumn.py
Products/DataGridField/WeekColumn.py
Products/DataGridField/__init__.py
Products/DataGridField/config.py
Products/DataGridField/configure.zcml
Products/DataGridField/interfaces.py
Products/DataGridField/screenshot.png
Products/DataGridField/utils.py
Products/DataGridField/validators.py
Products/DataGridField/examples/DataGridDemoType.py
Products/DataGridField/examples/__init__.py
Products/DataGridField/locales/datagridfield.pot
Products/DataGridField/locales/manual.pot
Products/DataGridField/locales/rebuild_i18n.sh
Products/DataGridField/locales/de/LC_MESSAGES/datagridfield.po
Products/DataGridField/locales/en/LC_MESSAGES/datagridfield.po
Products/DataGridField/locales/es/LC_MESSAGES/datagridfield.po
Products/DataGridField/locales/fr/LC_MESSAGES/datagridfield.po
Products/DataGridField/locales/it/LC_MESSAGES/datagridfield.po
Products/DataGridField/locales/nl/LC_MESSAGES/datagridfield.po
Products/DataGridField/locales/pt_BR/LC_MESSAGES/datagridfield.po
Products/DataGridField/profiles/default/metadata.xml
Products/DataGridField/profiles/default/skins.xml
