Metadata-Version: 1.0
Name: Products.DataGridField
Version: 1.9.1
Summary: A table input component for Plone.
Home-page: http://plone.org/products/datagridfield
Author: Mikko Ohtamaa
Author-email: info@redinnovation.com
License: GPL
Keywords: Plone DataGridField Archetypes
Platform: UNKNOWN
Classifier: Programming Language :: Python
Classifier: Programming Language :: Python :: 2.6
Classifier: Programming Language :: Python :: 2.7
Classifier: Topic :: Software Development :: Libraries :: Python Modules
Classifier: Framework :: Plone
Classifier: Framework :: Plone :: 4.0
Classifier: Framework :: Plone :: 4.1
Classifier: Framework :: Plone :: 4.2
Classifier: Framework :: Plone :: 4.3
Classifier: Framework :: Zope2
Classifier: Development Status :: 5 - Production/Stable
